tap_bls/__init__.py
tap_bls/client.py
tap_bls/create_schemas.py
tap_bls/discover.py
tap_bls/streams.py
tap_bls/sync.py
tap_bls/update_state.py
tap_bls-0.2.0.dist-info/LICENSE
tap_bls-0.2.0.dist-info/METADATA
tap_bls-0.2.0.dist-info/WHEEL
tap_bls-0.2.0.dist-info/entry_points.txt
tap_bls-0.2.0.dist-info/top_level.txt
tap_bls-0.2.0.dist-info/RECORD
