Metadata-Version: 2.1
Name: tap-bls
Version: 0.2.0
Summary: Singer.io tap for extracting data from the Bureau of Labor Statistics API 2.0
Home-page: https://github.com/frasermarlow/tap-bls
Author: Stitch + Fraser Marlow
Author-email: tap.bls@frasermarlow.com
Classifier: Programming Language :: Python :: 3 :: Only
Classifier: License :: OSI Approved :: MIT License
Classifier: Operating System :: OS Independent
Requires-Python: >=3.5
License-File: LICENSE
Requires-Dist: singer-python ==5.9.0
Requires-Dist: singer-tools ==0.4.1
Requires-Dist: requests ==2.32.2
Requires-Dist: backoff ==1.8.0
Requires-Dist: jsonschema ==2.6.0
Requires-Dist: pylint ==1.8.3
Requires-Dist: pytz ==2018.4
Requires-Dist: pytzdata ==2020.1
Requires-Dist: simplejson ==3.11.1
Requires-Dist: singer-encodings ==0.0.3
Requires-Dist: python-dateutil ==2.8.2
